pytspl/__init__.py
pytspl/data/foreign_exchange/B1.csv
pytspl/data/foreign_exchange/B2t.csv
pytspl/data/foreign_exchange/FX_1538755200.csv
pytspl/data/foreign_exchange/FX_1538756100.csv
pytspl/data/foreign_exchange/FX_1538758800.csv
pytspl/data/foreign_exchange/FX_1540239661.csv
pytspl/data/foreign_exchange/FX_1540239674.csv
pytspl/data/foreign_exchange/FX_1540239681.csv
pytspl/data/foreign_exchange/flow_FX_1538755200.csv
pytspl/data/internet/as19990110.txt
pytspl/data/internet/as20000102.txt
pytspl/data/lastfm-dataset-1K/B1-artist.csv
pytspl/data/lastfm-dataset-1K/B1.csv
pytspl/data/lastfm-dataset-1K/B2t-artist.csv
pytspl/data/lastfm-dataset-1K/B2t.csv
pytspl/data/lastfm-dataset-1K/flow-artist.csv
pytspl/data/lastfm-dataset-1K/flow.csv
pytspl/data/london_street/LondonEdges.csv
pytspl/data/london_street/LondonNodes.csv
pytspl/data/minnesota/B1.csv
pytspl/data/minnesota/B2.csv
pytspl/data/minnesota/coordinate.csv
pytspl/data/opsahl-powergrid/README.opsahl-powergrid
pytspl/data/opsahl-powergrid/meta.opsahl-powergrid
pytspl/data/opsahl-powergrid/out.opsahl-powergrid
pytspl/data/paper_data/B1.csv
pytspl/data/paper_data/B2t.csv
pytspl/data/paper_data/coordinates.csv
pytspl/data/paper_data/edges.csv
pytspl/data/paper_data/flow.csv
pytspl/data/paper_data/network.tntp
pytspl/data/transportation_networks/README.md
pytspl/data/transportation_networks/anaheim/AnaheimNetwork.pdf
pytspl/data/transportation_networks/anaheim/README.md
pytspl/data/transportation_networks/anaheim/anaheim.geojson
pytspl/data/transportation_networks/anaheim/anaheim_flow.tntp
pytspl/data/transportation_networks/anaheim/anaheim_net.tntp
pytspl/data/transportation_networks/anaheim/anaheim_node.tntp
pytspl/data/transportation_networks/anaheim/anaheim_trips.tntp
pytspl/data/transportation_networks/barcelona/README.md
pytspl/data/transportation_networks/barcelona/barcelona_flow.tntp
pytspl/data/transportation_networks/barcelona/barcelona_net.tntp
pytspl-0.1.5.dist-info/LICENSE
pytspl-0.1.5.dist-info/METADATA
pytspl-0.1.5.dist-info/WHEEL
pytspl-0.1.5.dist-info/RECORD
