Metadata-Version: 2.1
Name: pytspl
Version: 0.1.5
Summary: A Python library for Topological Signal Processing and Learning.
Home-page: https://github.com/irtazahashmi/pytspl
License: MIT
Author: Irtaza Hashmi
Author-email: irtazahashmi@gmail.com
Requires-Python: >=3.11,<4.0
Classifier: License :: OSI Approved :: MIT License
Classifier: Programming Language :: Python :: 3
Classifier: Programming Language :: Python :: 3.11
Classifier: Programming Language :: Python :: 3.12
Requires-Dist: coverage (>=7.3.2,<8.0.0)
Requires-Dist: cvxpy (>=1.5.1,<2.0.0)
Requires-Dist: gpytorch (>=1.11,<2.0)
Requires-Dist: gudhi (>=3.9.0,<4.0.0)
Requires-Dist: hypernetx (>=1.2.5,<2.0.0)
Requires-Dist: ipykernel (>=6.29.4,<7.0.0)
Requires-Dist: matplotlib (>=3.8.2,<4.0.0)
Requires-Dist: networkx (>=2.8.8,<3.0.0)
Requires-Dist: numpydoc (>=1.7.0,<2.0.0)
Requires-Dist: pandas (>=2.1.1,<3.0.0)
Requires-Dist: pyproject-flake8 (>=7.0.0,<8.0.0)
Requires-Dist: pytest (>=7.4.3,<8.0.0)
Requires-Dist: scipy (>=1.11.4,<2.0.0)
Requires-Dist: setuptools (>=71.1.0,<72.0.0)
Requires-Dist: sphinx (>=7.2.6,<8.0.0)
Requires-Dist: sphinx-autoapi (>=3.2.1,<4.0.0)
Requires-Dist: sphinx-rtd-theme (>=2.0.0,<3.0.0)
Requires-Dist: sphinxcontrib-bibtex (>=2.6.2,<3.0.0)
Requires-Dist: torch (>=2.3.1,<3.0.0)
Requires-Dist: torcheval (>=0.0.7,<0.0.8)
Requires-Dist: torchvision (>=0.18.0,<0.19.0)
Requires-Dist: trimesh (>=4.0.10,<5.0.0)
Project-URL: Documentation, https://pytspl.readthedocs.io/en/latest/
Project-URL: Repository, https://github.com/irtazahashmi/pytspl
